{"type":"FeatureCollection","features":[{"type":"Feature","properties":{"SCHOOL":"Tomorrow River Virtual Charter","DISTRICT":"Tomorrow River","SCH_TYPE":"Elementary School","LOW_GRADE":"K4","HIGH_GRD":8,"TYPE_DESC":"Public school","SCH_CAT":"Regular","CHARTER":"Charter","FULL_ADDR":"10186 County Road MM  Amherst Junction WI  54407-9053","PHYS_COUNT":"Portage","CESA":5,"DPI_KEY":1570,"DIST_CODE":126,"SCH_CODE":140,"UNIQUE":1260140,"NCES_DIST":5500330,"NCES_SCH":3063,"Comment_Vax":"Report received","PctMetMinRequirements_Vax":40},"geometry":{"type":"Point","coordinates":[-89.31261,44.46886]}},{"type":"Feature","properties":{"SCHOOL":"Independence Middle School ","DISTRICT":"Independence","SCH_TYPE":"Middle School","LOW_GRADE":6,"HIGH_GRD":8,"TYPE_DESC":"Public school","SCH_CAT":"Regular","CHARTER":"No","FULL_ADDR":"23786 Indee Blvd  Independence WI  54747-9095","PHYS_COUNT":"Trempealeau","CESA":4,"DPI_KEY":920,"DIST_CODE":2632,"SCH_CODE":250,"UNIQUE":26320250,"NCES_DIST":5506810,"NCES_SCH":2990,"Comment_Vax":"Report received","PctMetMinRequirements_Vax":41},"geometry":{"type":"Point","coordinates":[-91.421309,44.368663]}},{"type":"Feature","properties":{"SCHOOL":"Laurel High School","DISTRICT":"Viroqua Area","SCH_TYPE":"High School","LOW_GRADE":9,"HIGH_GRD":12,"TYPE_DESC":"Public school","SCH_CAT":"Regular","CHARTER":"Charter","FULL_ADDR":"100 Blackhawk Dr  Viroqua WI  54665","PHYS_COUNT":"Vernon","CESA":4,"DPI_KEY":70096,"DIST_CODE":5985,"SCH_CODE":410,"UNIQUE":59850410,"NCES_DIST":5515360,"NCES_SCH":1936,"Comment_Vax":"Report received","PctMetMinRequirements_Vax":46},"geometry":{"type":"Point","coordinates":[-90.900843,43.558921]}}]}